agent.py
cli.py
securesyntax-0.1.0.dist-info/licenses/LICENSE
securesyntax-0.1.0.dist-info/METADATA
securesyntax-0.1.0.dist-info/WHEEL
securesyntax-0.1.0.dist-info/entry_points.txt
securesyntax-0.1.0.dist-info/top_level.txt
securesyntax-0.1.0.dist-info/RECORD
