Metadata-Version: 2.4
Name: securesyntax
Version: 0.1.0
Summary: Secure Syntax - AI-powered code analyzer and bug fixer
Author: Crynix
License: MIT
Requires-Python: >=3.10
License-File: LICENSE
Requires-Dist: colorama
Requires-Dist: requests
Requires-Dist: google-genai<1.21.0,>=1.20.0
Requires-Dist: anyio<5.0.0,>=4.8.0
Dynamic: license-file
